pydantic_custom_types/VERSION
pydantic_custom_types/__init__.py
pydantic_custom_types/active_directory/__init__.py
pydantic_custom_types/active_directory/ad_groups.py
pydantic_custom_types/active_directory/ad_users.py
pydantic_custom_types/active_directory/util.py
pydantic_custom_types/dns/__init__.py
pydantic_custom_types/dns/hostname.py
pydantic_custom_types/ip/__init__.py
pydantic_custom_types/ip/ipv4.py
pydantic_custom_types/kubernetes/__init__.py
pydantic_custom_types/kubernetes/base_name.py
pydantic_custom_types/kubernetes/namespace_name.py
pydantic_custom_types/kubernetes/secret.py
pydantic_custom_types/version.py
pydantic_custom_types-0.2.2.dist-info/METADATA
pydantic_custom_types-0.2.2.dist-info/WHEEL
pydantic_custom_types-0.2.2.dist-info/LICENSE
pydantic_custom_types-0.2.2.dist-info/RECORD
