Metadata-Version: 2.1
Name: pydantic-custom-types
Version: 0.2.2
Summary: Custom types for pydantic used in SRE peipelins for validation input vars
Author: per lejon
Author-email: per.lejon@netigate.se
Requires-Python: >=3.10,<4.0
Classifier: Programming Language :: Python :: 3
Classifier: Programming Language :: Python :: 3.10
Classifier: Programming Language :: Python :: 3.11
Requires-Dist: build (>=0.9.0,<0.10.0)
Requires-Dist: python-decouple (>=3.6,<4.0)
